nordvpn_switcher/__init__.py
nordvpn_switcher/demo.py
nordvpn_switcher/nordvpn_switch.py
nordvpn_switcher/NordVPN_options/__init__.py
nordvpn_switcher/NordVPN_options/countrylist.txt
nordvpn_switcher/NordVPN_options/options_linux.txt
nordvpn_switcher/NordVPN_options/__pycache__/__init__.cpython-38.pyc
nordvpn_switcher-0.3.0.dist-info/LICENSE
nordvpn_switcher-0.3.0.dist-info/METADATA
nordvpn_switcher-0.3.0.dist-info/WHEEL
nordvpn_switcher-0.3.0.dist-info/top_level.txt
nordvpn_switcher-0.3.0.dist-info/RECORD
