Metadata-Version: 2.1
Name: nordvpn_switcher
Version: 0.3.0
Summary: Rotate between different NordVPN servers with ease. Works both on Linux and Windows without any required changes to your code!
Home-page: https://github.com/kboghe/NordVPN-switcher
Author: Kristof Boghe
Author-email: kboghe@gmail.com
License: Apache License 2.0
Platform: UNKNOWN
